kontroller/__init__.py
kontroller/base.py
kontroller/version.py
kontroller-0.0.2.dist-info/DESCRIPTION.rst
kontroller-0.0.2.dist-info/METADATA
kontroller-0.0.2.dist-info/metadata.json
kontroller-0.0.2.dist-info/RECORD
kontroller-0.0.2.dist-info/top_level.txt
kontroller-0.0.2.dist-info/WHEEL
