Metadata-Version: 2.0
Name: kontroller
Version: 0.0.2
Summary: Python lib for kubernetes controllers
Home-page: https://github.com/caruccio/kontroller
Author: Mateus Caruccio
Author-email: mateus.caruccio@getupcloud.com
License: Apache License Version 2.0
Keywords: Kubernetes
Platform: UNKNOWN
Classifier: Development Status :: 3 - Alpha
Classifier: Topic :: Utilities
Classifier: Intended Audience :: Developers
Classifier: Intended Audience :: Information Technology
Classifier: License :: OSI Approved :: Apache Software License
Classifier: Operating System :: OS Independent
Classifier: Programming Language :: Python
Classifier: Programming Language :: Python :: 2
Classifier: Programming Language :: Python :: 2.7
Classifier: Programming Language :: Python :: 3
Classifier: Programming Language :: Python :: 3.4
Classifier: Programming Language :: Python :: 3.5
Classifier: Programming Language :: Python :: 3.6
